pybigtools-0.2.3.dist-info/METADATA
pybigtools-0.2.3.dist-info/WHEEL
pybigtools-0.2.3.dist-info/licenses/LICENSE
pybigtools/__init__.py
pybigtools/pybigtools.cpython-310-aarch64-linux-gnu.so
pybigtools-0.2.3.dist-info/RECORD
