Metadata-Version: 2.3
Name: pybigtools
Version: 0.2.3
Classifier: Development Status :: 4 - Beta
Classifier: Operating System :: OS Independent
Classifier: Topic :: Scientific/Engineering :: Bio-Informatics
Classifier: Programming Language :: Rust
Classifier: Programming Language :: Python
Classifier: Programming Language :: Python :: 3
Requires-Dist: numpy
Requires-Dist: pytest ; extra == 'test'
Requires-Dist: smart-open[http] ; extra == 'test'
Requires-Dist: ruff ; extra == 'dev'
Provides-Extra: test
Provides-Extra: dev
License-File: LICENSE
Summary: Python bindings to the Bigtools Rust library for high-performance BigWig and BigBed I/O
Keywords: bigwig,bigbed,bbi,bioinformatics,genomics,kent,ucsc,rust
Author: Jack <jackh726@gmail.com>
Author-email: Jack <jackh726@gmail.com>
License: MIT
Project-URL: homepage, https://github.com/jackh726/bigtools
Project-URL: documentation, https://bigtools.readthedocs.io
Project-URL: repository, https://github.com/jackh726/bigtools
